noctis/__init__.py
noctis/agent.py
noctis/cli.py
noctis/predefined_agents.py
noctis/tools.py
noctis/memory/sqlite.py
noctis/models/ollama_adapter.py
noctis/models/openai_adapter.py
noctis_ai-1.0.1.dist-info/METADATA
noctis_ai-1.0.1.dist-info/WHEEL
noctis_ai-1.0.1.dist-info/entry_points.txt
noctis_ai-1.0.1.dist-info/top_level.txt
noctis_ai-1.0.1.dist-info/RECORD
